{"swagger":"2.0","info":{"version":"1.0.0","title":"EVERIS rest API","description":"EVERIS API to make control over the switches using OVSDB Protocol"},"basePath":"/onos/org.everis","produces":["application/json"],"consumes":["application/json"],"tags":[{"name":"config","description":"Possible REST APIs to make changes in the switches of the ONOS Cluster"}],"paths":{"/config/sample":{"get":{"tags":["config"],"summary":"Get hello world greeting","description":"","parameters":[],"responses":{"200":{"description":"successful operation"},"default":{"description":"Unexpected error"}}}},"/config/{ovsdb-ip}/bridge/{bridge-name}":{"post":{"tags":["config"],"summary":"Create a bridge using the IP of a known Device Manager","description":"","parameters":[{"name":"ovsdb-ip","in":"path","type":"string","description":"OVSDB IP Address","required":true},{"name":"bridge-name","in":"path","type":"string","description":"Bridge Name","required":true}],"consumes":["application/json"],"produces":["application/json"],"responses":{"200":{"description":"successful operation"},"default":{"description":"Unexpected error"}}},"delete":{"tags":["config"],"summary":"Delete the bridge with the given information","description":"","parameters":[{"name":"ovsdb-ip","in":"path","type":"string","description":"OVSDB IP Address","required":true},{"name":"bridge-name","in":"path","type":"string","description":"Bridge Name to delete","required":true}],"consumes":["application/json"],"produces":["application/json"],"responses":{"200":{"description":"successful operation"},"default":{"description":"Unexpected error"}}}},"/config/{ovsdb-ip}/bridge/{bridge-name}/port/{port-name}":{"post":{"tags":["config"],"summary":"Add a port in the bridge with the given information","description":"","parameters":[{"name":"ovsdb-ip","in":"path","type":"string","description":"OVSDB IP Address","required":true},{"name":"bridge-name","in":"path","type":"string","description":"Bridge Name","required":true},{"name":"port-name","in":"path","type":"string","description":"Port name to add","required":true}],"consumes":["application/json"],"produces":["application/json"],"responses":{"200":{"description":"successful operation"},"default":{"description":"Unexpected error"}}},"delete":{"tags":["config"],"summary":"Delete the port of a bridge","description":"","parameters":[{"name":"ovsdb-ip","in":"path","type":"string","description":"OVSDB IP Address","required":true},{"name":"bridge-name","in":"path","type":"string","description":"Bridge Name","required":true},{"name":"port-name","in":"path","type":"string","description":"Port Name to delete","required":true}],"consumes":["application/json"],"produces":["application/json"],"responses":{"200":{"description":"successful operation"},"default":{"description":"Unexpected error"}}}}},"definitions":{}}
